injecta/autowiring/ArgumentResolver.py
injecta/autowiring/ArgumentsAutowirer.py
injecta/autowiring/ArgumentsAutowirerTest.py
injecta/autowiring/AutowiringCompilerPass.py
injecta/compiler/CompilerPassInterface.py
injecta/config/ConfigLoader.py
injecta/config/ConfigLoaderAndMerger.py
injecta/config/ConfigMerger.py
injecta/config/ConfigMergerTest.py
injecta/config/ConfigPathsResolver.py
injecta/config/ConfigReaderInterface.py
injecta/config/ImportDefinitionResolver.py
injecta/config/YamlConfigReader.py
injecta/config/YamlConfigReaderTest/basic/config.yaml
injecta/config/YamlConfigReaderTest/basic/sub_config.yaml
injecta/config/YamlConfigReaderTest/basic/sub_config2.yaml
injecta/config/YamlConfigReaderTest/basic/sub_sub_config.yaml
injecta/config/YamlConfigReaderTest/basic/sub_sub_config2.yaml
injecta/config/YamlConfigReaderTest/basic/sub_sub_config3.yaml
injecta/config/YamlConfigReaderTest/basic/sub_sub_config4.yaml
injecta/config/YamlConfigReaderTest/search/_config/config.yaml
injecta/config/YamlConfigReaderTest/search/mypackage/sub_config.yaml
injecta/config/YamlConfigReaderTest/search/mypackage/subpackage/sub_sub_config.yaml
injecta/config/YamlConfigReaderTest.py
injecta/container/ContainerBuild.py
injecta/container/ContainerBuilder.py
injecta/container/ContainerInitializer.py
injecta/container/ContainerInitializerTest.py
injecta/container/ContainerInitializerTest_config.yaml
injecta/container/ContainerInterface.py
injecta/container/Hooks.py
injecta/dtype/AbstractType.py
injecta/dtype/DType.py
injecta/dtype/FullnameTest.py
injecta/dtype/ListType.py
injecta/dtype/fullname.py
injecta/generator/ContainerGenerator.py
injecta/generator/DiService.py
injecta/generator/ObjectGenerator.py
injecta/generator/ServiceGenerator.py
injecta/generator/ServiceMethodNameTranslator.py
injecta/generator/Tag2ServicesPreparer.py
injecta/generator/Tag2ServicesPreparerTest.py
injecta/generator/container_template.py
injecta/lib_root.py
injecta/mocks/Args.py
injecta/mocks/ArgsKwargs.py
injecta-0.10.2.dist-info/LICENSE
injecta-0.10.2.dist-info/WHEEL
injecta-0.10.2.dist-info/METADATA
injecta-0.10.2.dist-info/RECORD
