Metadata-Version: 2.1
Name: injecta
Version: 0.10.2
Summary: Dependency Injection Container Library
Home-page: https://github.com/pyfony/injecta
License: MIT
Author: Jiri Koutny
Author-email: jiri.koutny@datasentics.com
Requires-Python: >=3.7,<4.0
Classifier: License :: OSI Approved :: MIT License
Classifier: Operating System :: OS Independent
Classifier: Programming Language :: Python :: 3
Classifier: Programming Language :: Python :: 3.7
Classifier: Programming Language :: Python :: 3.8
Classifier: Programming Language :: Python :: 3.9
Requires-Dist: PyYAML (>=5.1,<6.0)
Requires-Dist: python-box (>=3.4,<4.0)
Requires-Dist: tomlkit (>=0.5.8,<1.0.0)
Project-URL: Repository, https://github.com/pyfony/injecta
